binimage/__init__.py
binimage/cli.py
binimage/decoder.py
binimage/utils.py
binimage-1.6.0.dist-info/licenses/LICENSE
binimage-1.6.0.dist-info/METADATA
binimage-1.6.0.dist-info/WHEEL
binimage-1.6.0.dist-info/entry_points.txt
binimage-1.6.0.dist-info/top_level.txt
binimage-1.6.0.dist-info/RECORD
