Metadata-Version: 2.4
Name: binimage
Version: 1.6.0
Summary: Extract binary from images (OCR or grid) and decode to text, saving to results.txt
Author-email: vesper <vesper.oneold@gmail.com>
License: MIT
Keywords: binary,image,OCR,grid,decode,persian,english
Classifier: Programming Language :: Python :: 3
Classifier: Programming Language :: Python :: 3 :: Only
Classifier: License :: OSI Approved :: MIT License
Classifier: Operating System :: OS Independent
Classifier: Topic :: Multimedia :: Graphics
Classifier: Topic :: Text Processing :: General
Requires-Python: >=3.9
License-File: LICENSE
Requires-Dist: Pillow>=10.0.0
Requires-Dist: numpy>=1.24.0
Provides-Extra: ocr
Requires-Dist: pytesseract>=0.3.10; extra == "ocr"
Provides-Extra: dev
Requires-Dist: pytest>=7.0; extra == "dev"
Requires-Dist: flake8>=7.0; extra == "dev"
Dynamic: license-file
